hdrglobal/__init__.py
hdrglobal/processor.py
hdrglobal/resources/__init__.py
hdrglobal/resources/crf_calc.py
hdrglobal/resources/crfio.py
hdrglobal/resources/hdr_merge.py
hdrglobal/resources/ldr_sharpen.py
hdrglobal/resources/tonemaping.py
hdr_global_processing-0.1.8.dist-info/METADATA
hdr_global_processing-0.1.8.dist-info/WHEEL
hdr_global_processing-0.1.8.dist-info/top_level.txt
hdr_global_processing-0.1.8.dist-info/RECORD
