Metadata-Version: 2.1
Name: hdr-global-processing
Version: 0.1.8
Summary: Petri Global Tonemapping Package
Home-page: https://github.com/Elessar11777
Author: Elessar11777
Author-email: Elessar11777@gmail.com
License: GPL
Requires-Dist: numpy
Requires-Dist: opencv-python
